pytest_typechecker/__init__.py
pytest_typechecker/checkers.py
pytest_typechecker/plugin.py
pytest_typechecker-0.3.3.dist-info/entry_points.txt
pytest_typechecker-0.3.3.dist-info/WHEEL
pytest_typechecker-0.3.3.dist-info/METADATA
pytest_typechecker-0.3.3.dist-info/RECORD
