Metadata-Version: 2.1
Name: pytest-typechecker
Version: 0.3.3
Summary: Run type checkers on specified test files
Home-page: https://github.com/vivax3794/pytest-typechecker
License: MIT
Keywords: pytest,unittest,type hinting,pyright,mypy
Author: vivax
Author-email: vivax3794@protonmail.com
Requires-Python: >=3.6
Classifier: Environment :: Plugins
Classifier: Framework :: Pytest
Classifier: Intended Audience :: Developers
Classifier: License :: OSI Approved :: MIT License
Classifier: Natural Language :: English
Classifier: Programming Language :: Python :: 3
Classifier: Programming Language :: Python :: 3.10
Classifier: Programming Language :: Python :: 3.6
Classifier: Programming Language :: Python :: 3.7
Classifier: Programming Language :: Python :: 3.8
Classifier: Programming Language :: Python :: 3.9
Classifier: Topic :: Software Development :: Testing
Requires-Dist: mypy (>=0.931,<0.932)
Requires-Dist: pyright (>=0.0.13,<0.0.14)
Requires-Dist: pytest (>=6.2.5,<7.0.0)
Project-URL: Repository, https://github.com/vivax3794/pytest-typechecker
